ecpick/__init__.py
ecpick/ecpick.py
ecpick/model.py
ecpick/util/__init__.py
ecpick/util/dataset.py
ecpick/util/downloader.py
ecpick/util/logger.py
ecpick/util/seq_encoder.py
ecpick/util/stopwatch.py
tests/__init__.py
tests/ecpick_test.py
ecpick-0.0.1.dist-info/LICENSE.md
ecpick-0.0.1.dist-info/METADATA
ecpick-0.0.1.dist-info/WHEEL
ecpick-0.0.1.dist-info/top_level.txt
ecpick-0.0.1.dist-info/RECORD
