Metadata-Version: 2.1
Name: ecpick
Version: 0.0.1
Summary: Enzyme Commission Number Prediction
Home-page: https://github.com/datax-lab/ECPICK
Author: MINGYU PARK@Sunmoon University
Author-email: duveen@duveen.me
Project-URL: Bug Reports, https://github.com/datax-lab/ECPICK/issue
Project-URL: Source, https://github.com/datax-lab/ECPICK
Keywords: enzyme,ec number,prediction
Classifier: Development Status :: 3 - Alpha
Classifier: Environment :: GPU
Classifier: Intended Audience :: Science/Research
Classifier: License :: OSI Approved :: MIT License
Classifier: Operating System :: OS Independent
Classifier: Programming Language :: Python :: 3
Classifier: Programming Language :: Python :: 3.6
Classifier: Programming Language :: Python :: 3.7
Classifier: Programming Language :: Python :: 3.8
Classifier: Programming Language :: Python :: 3.9
Classifier: Programming Language :: Python :: 3 :: Only
Classifier: Topic :: Scientific/Engineering :: Artificial Intelligence
Classifier: Topic :: Scientific/Engineering :: Bio-Informatics
License-File: LICENSE.md
Requires-Dist: biopython (==1.78)
Requires-Dist: numpy (==1.23.2)
Requires-Dist: torch (==1.12.1)
Requires-Dist: torchvision (==0.13.1)
Requires-Dist: torchaudio (==0.12.1)
Requires-Dist: scikit-learn (==1.1.2)
Requires-Dist: tqdm (==4.64.0)
Provides-Extra: dev
Requires-Dist: pytest ; extra == 'dev'
